README.md
setup.py
mysqlcommand/__init__.py
mysqlcommand/mysqlcommand.py
mysqlcommand/parameters.py
mysqlcommand.egg-info/PKG-INFO
mysqlcommand.egg-info/SOURCES.txt
mysqlcommand.egg-info/dependency_links.txt
mysqlcommand.egg-info/requires.txt
mysqlcommand.egg-info/top_level.txt
mysqlcommand.egg-info/zip-safe