Metadata-Version: 2.1
Name: mysqlcommand
Version: 0.1.1
Summary: Mysql query builder
Home-page: https://github.com/wfreeman8/mysqlcommand
Author: Worth Freeman
Author-email: wfreeman8@users.noreply.github.com
License: MIT
Keywords: mysqlcommand
Platform: UNKNOWN
Requires-Python: >=3.6
